iacgen/__init__.py
iacgen/__main__.py
iacgen/cli.py
iacgen/config.py
iacgen/exceptions.py
iacgen/preset_loader.py
iacgen/py.typed
iacgen/renderer.py
iacgen/validator.py
iacgen/presets/__init__.py
iacgen/presets/full-stack.yml
iacgen/presets/microservice.yml
iacgen/presets/simple-vpc.yml
iacgen/templates/__init__.py
iacgen/templates/main.tf.j2
iacgen/templates/outputs.tf.j2
iacgen/templates/terraform.tfvars.j2
iacgen/templates/variables.tf.j2
iacgen/templates/modules/alb/main.tf.j2
iacgen/templates/modules/alb/outputs.tf.j2
iacgen/templates/modules/alb/variables.tf.j2
iacgen/templates/modules/eks/main.tf.j2
iacgen/templates/modules/eks/outputs.tf.j2
iacgen/templates/modules/eks/variables.tf.j2
iacgen/templates/modules/service/main.tf.j2
iacgen/templates/modules/service/outputs.tf.j2
iacgen/templates/modules/service/variables.tf.j2
iacgen/templates/modules/vpc/main.tf.j2
iacgen/templates/modules/vpc/outputs.tf.j2
iacgen/templates/modules/vpc/variables.tf.j2
iacgen-1.1.0.dist-info/licenses/LICENSE
iacgen-1.1.0.dist-info/METADATA
iacgen-1.1.0.dist-info/WHEEL
iacgen-1.1.0.dist-info/entry_points.txt
iacgen-1.1.0.dist-info/top_level.txt
iacgen-1.1.0.dist-info/RECORD
