Metadata-Version: 2.4
Name: iacgen
Version: 1.1.0
Summary: A CLI tool that automatically generates Terraform infrastructure blueprints based on user input
Author: Nana Appiah
License: MIT
Project-URL: Homepage, https://github.com/JRcodes/iac-generator
Project-URL: Documentation, https://github.com/JRcodes/iac-generator#readme
Project-URL: Repository, https://github.com/JRcodes/iac-generator
Project-URL: Bug Tracker, https://github.com/JRcodes/iac-generator/issues
Project-URL: Changelog, https://github.com/JRcodes/iac-generator/#CHANGELOG
Keywords: terraform,infrastructure,iac,aws,cli,devops
Classifier: Development Status :: 4 - Beta
Classifier: Intended Audience :: Developers
Classifier: Intended Audience :: System Administrators
Classifier: License :: OSI Approved :: MIT License
Classifier: Programming Language :: Python :: 3
Classifier: Programming Language :: Python :: 3 :: Only
Classifier: Programming Language :: Python :: 3.10
Classifier: Programming Language :: Python :: 3.11
Classifier: Programming Language :: Python :: 3.12
Classifier: Topic :: Software Development :: Code Generators
Classifier: Topic :: System :: Systems Administration
Classifier: Typing :: Typed
Requires-Python: >=3.10
License-File: LICENSE
Requires-Dist: typer>=0.9.0
Requires-Dist: jinja2>=3.1.0
Requires-Dist: pyyaml>=6.0
Requires-Dist: pydantic>=2.0
Requires-Dist: rich>=13.0
Provides-Extra: dev
Requires-Dist: pytest>=7.0; extra == "dev"
Requires-Dist: pytest-cov>=4.0; extra == "dev"
Requires-Dist: black>=23.0; extra == "dev"
Requires-Dist: ruff>=0.1.0; extra == "dev"
Requires-Dist: mypy>=1.0; extra == "dev"
Dynamic: license-file
